test_jaws/__init__.py
test_jaws/aaws2nc.py
test_jaws/analysis.py
test_jaws/common.py
test_jaws/gcnet2nc.py
test_jaws/imau2nc.py
test_jaws/jaws.py
test_jaws/promice2nc.py
test_jaws/sunposition.py
test_jaws/resources/stations.txt
test_jaws/resources/aaws/columns.txt
test_jaws/resources/aaws/ds.json
test_jaws/resources/aaws/encoding.json
test_jaws/resources/gcnet/columns.txt
test_jaws/resources/gcnet/ds.json
test_jaws/resources/gcnet/encoding.json
test_jaws/resources/gcnet/quality_control.json
test_jaws/resources/imau/ant/columns.txt
test_jaws/resources/imau/ant/ds.json
test_jaws/resources/imau/ant/encoding.json
test_jaws/resources/imau/grl/columns.txt
test_jaws/resources/imau/grl/ds.json
test_jaws/resources/imau/grl/encoding.json
test_jaws/resources/promice/aliases.txt
test_jaws/resources/promice/columns.txt
test_jaws/resources/promice/ds.json
test_jaws/resources/promice/encoding.json
test_jaws-0.3.dist-info/METADATA
test_jaws-0.3.dist-info/RECORD
test_jaws-0.3.dist-info/WHEEL
test_jaws-0.3.dist-info/entry_points.txt
test_jaws-0.3.dist-info/top_level.txt
tests/__init__.py
tests/test.py
