Metadata-Version: 2.1
Name: test-jaws
Version: 0.3
Summary: Software to convert idiosyncratic ASCII formats to netCDF formats
Home-page: https://github.com/jaws/jaws
Author: Ajay Saini
Author-email: ajcse1@gmail.com
License: UNKNOWN
Keywords: xarray,netcdf,pandas,data,science,network,meteorology,climate,automated,weather,stations
Platform: any
Classifier: Development Status :: 3 - Alpha
Classifier: Programming Language :: Python :: 2
Classifier: Programming Language :: Python :: 2.7
Classifier: Programming Language :: Python :: 3
Classifier: Programming Language :: Python :: 3.6
Classifier: Intended Audience :: Science/Research
Classifier: License :: OSI Approved :: Apache Software License
Classifier: Topic :: Scientific/Engineering :: Atmospheric Science
Classifier: Topic :: Software Development :: Libraries :: Python Modules
Classifier: Operating System :: OS Independent
Requires-Dist: pandas
Requires-Dist: numpy
Requires-Dist: xarray
Requires-Dist: pytz
Requires-Dist: matplotlib
Requires-Dist: netcdf4
